{
  "teams": [
    {
      "name": "Frontend Platform",
      "email": "frontend-platform@company.com",
      "responsibilityArea": "frontend"
    },
    {
      "name": "Backend Platform",
      "email": "backend-platform@company.com",
      "responsibilityArea": "backend"
    },
    {
      "name": "Data Platform",
      "email": "data-platform@company.com",
      "responsibilityArea": "data"
    },
    {
      "name": "DevOps",
      "email": "devops@company.com",
      "responsibilityArea": "infrastructure"
    },
    {
      "name": "Security",
      "email": "security@company.com",
      "responsibilityArea": "security"
    },
    {
      "name": "Platform Team",
      "email": "platform-team@company.com",
      "responsibilityArea": "platform"
    }
  ],
  "technologies": [
    {
      "name": "Angular",
      "category": "framework",
      "vendor": "Google",
      "lastReviewed": "2025-09-15"
    },
    {
      "name": "Node.js",
      "category": "runtime",
      "vendor": "OpenJS Foundation",
      "lastReviewed": "2025-10-01"
    },
    {
      "name": "PostgreSQL",
      "category": "database",
      "vendor": "PostgreSQL Global Development Group",
      "lastReviewed": "2025-10-01"
    },
    {
      "name": "Neo4j",
      "category": "database",
      "vendor": "Neo4j Inc.",
      "lastReviewed": "2025-10-01"
    },
    {
      "name": "MongoDB",
      "category": "database",
      "vendor": "MongoDB Inc.",
      "lastReviewed": "2025-09-20"
    },
    {
      "name": "Docker",
      "category": "container",
      "vendor": "Docker Inc.",
      "lastReviewed": "2025-10-01"
    },
    {
      "name": "MySQL",
      "category": "database",
      "vendor": "Oracle",
      "lastReviewed": "2025-09-01"
    },
    {
      "name": "Redis",
      "category": "cache",
      "vendor": "Redis Ltd.",
      "lastReviewed": "2025-10-01"
    }
  ],
  "versions": [
    {
      "technologyName": "Node.js",
      "version": "20.11.0",
      "releaseDate": "2024-01-09",
      "eolDate": "2026-04-30",
      "approved": true,
      "notes": "LTS version"
    },
    {
      "technologyName": "PostgreSQL",
      "version": "16.1",
      "releaseDate": "2023-11-09",
      "eolDate": "2028-11-09",
      "approved": true,
      "notes": "Latest stable version"
    },
    {
      "technologyName": "Neo4j",
      "version": "5.26.13",
      "releaseDate": "2024-10-01",
      "eolDate": "2027-10-01",
      "approved": true,
      "notes": "Community edition"
    }
  ],
  "relationships": {
    "technology_versions": [
      {
        "technology": "Node.js",
        "version": "20.11.0"
      },
      {
        "technology": "PostgreSQL",
        "version": "16.1"
      },
      {
        "technology": "Neo4j",
        "version": "5.26.13"
      }
    ],
    "team_technologies": [
      {
        "team": "Frontend Platform",
        "technology": "Angular"
      },
      {
        "team": "Backend Platform",
        "technology": "Node.js"
      },
      {
        "team": "Backend Platform",
        "technology": "Redis"
      },
      {
        "team": "Data Platform",
        "technology": "PostgreSQL"
      },
      {
        "team": "Data Platform",
        "technology": "Neo4j"
      },
      {
        "team": "Data Platform",
        "technology": "MongoDB"
      },
      {
        "team": "Data Platform",
        "technology": "MySQL"
      },
      {
        "team": "DevOps",
        "technology": "Docker"
      },
      {
        "team": "Platform Team",
        "technology": "Node.js"
      },
      {
        "team": "Platform Team",
        "technology": "Neo4j"
      }
    ]
  },
  "github_systems": {
    "_comment": "These systems are created by seed:github from github-repos.json. Relationships defined here are applied after GitHub seeding.",
    "team_systems": [
      {
        "team": "Platform Team",
        "system": "Polaris Technology Catalog"
      },
      {
        "team": "Platform Team",
        "system": "Catalyst"
      },
      {
        "team": "Platform Team",
        "system": "TSArchi"
      },
      {
        "team": "Platform Team",
        "system": "PlantKit"
      },
      {
        "team": "Platform Team",
        "system": "Karla"
      }
    ]
  },
  "approvals": {
    "team_technology_approvals": [
      {
        "team": "Frontend Platform",
        "technology": "Angular",
        "time": "migrate",
        "approvedAt": "2023-06-01",
        "deprecatedAt": "2024-06-01",
        "migrationTarget": "React",
        "notes": "Legacy projects only, migrate to React",
        "approvedBy": "Tech Lead"
      },
      {
        "team": "Backend Platform",
        "technology": "Node.js",
        "time": "invest",
        "approvedAt": "2024-01-15",
        "notes": "Primary backend runtime - strategic investment",
        "approvedBy": "Tech Lead"
      },
      {
        "team": "Backend Platform",
        "technology": "Redis",
        "time": "invest",
        "approvedAt": "2024-03-01",
        "notes": "Caching and session storage",
        "approvedBy": "Tech Lead"
      },
      {
        "team": "Data Platform",
        "technology": "PostgreSQL",
        "time": "invest",
        "approvedAt": "2024-01-15",
        "notes": "Primary relational database - strategic investment",
        "approvedBy": "Data Lead"
      },
      {
        "team": "Data Platform",
        "technology": "Neo4j",
        "time": "invest",
        "approvedAt": "2024-01-15",
        "notes": "Graph database for relationship-heavy data",
        "approvedBy": "Data Lead"
      },
      {
        "team": "Data Platform",
        "technology": "MongoDB",
        "time": "tolerate",
        "approvedAt": "2024-06-01",
        "notes": "Tolerated for specific document storage use cases",
        "approvedBy": "Data Lead"
      },
      {
        "team": "Data Platform",
        "technology": "MySQL",
        "time": "tolerate",
        "approvedAt": "2024-09-01",
        "notes": "Tolerated for legacy system compatibility",
        "approvedBy": "Data Lead"
      },
      {
        "team": "DevOps",
        "technology": "Docker",
        "time": "invest",
        "approvedAt": "2024-01-15",
        "notes": "Standard containerization platform",
        "approvedBy": "DevOps Lead"
      },
      {
        "team": "Platform Team",
        "technology": "Node.js",
        "time": "invest",
        "approvedAt": "2024-01-15",
        "notes": "Runtime for TypeScript projects",
        "approvedBy": "Platform Lead"
      },
      {
        "team": "Platform Team",
        "technology": "Neo4j",
        "time": "invest",
        "approvedAt": "2024-01-15",
        "notes": "Graph database for Polaris technology catalog",
        "approvedBy": "Platform Lead"
      }
    ]
  },
  "component_technologies": [
    {
      "componentName": "react",
      "packageManager": "npm",
      "technology": {
        "name": "React",
        "category": "framework",
        "vendor": "Meta"
      },
      "ownerTeam": "Frontend Platform",
      "stewardTeams": [
        "Frontend Platform"
      ],
      "policies": [
        "Technology Approval Required",
        "EOL Warning"
      ],
      "approvals": [
        {
          "team": "Frontend Platform",
          "time": "invest",
          "approvedAt": "2024-01-15",
          "notes": "Primary frontend framework - strategic investment",
          "approvedBy": "Tech Lead"
        }
      ]
    },
    {
      "componentName": "vue",
      "packageManager": "npm",
      "technology": {
        "name": "Vue",
        "category": "framework",
        "vendor": "Vue.js Team"
      },
      "ownerTeam": "Frontend Platform",
      "stewardTeams": [
        "Frontend Platform",
        "Platform Team"
      ],
      "policies": [
        "Technology Approval Required",
        "EOL Warning"
      ],
      "approvals": [
        {
          "team": "Frontend Platform",
          "time": "invest",
          "approvedAt": "2024-01-15",
          "notes": "Alternative frontend framework for specific use cases",
          "approvedBy": "Tech Lead"
        },
        {
          "team": "Platform Team",
          "time": "invest",
          "approvedAt": "2024-01-15",
          "notes": "Frontend framework for Polaris",
          "approvedBy": "Platform Lead"
        }
      ]
    },
    {
      "componentName": "express",
      "packageManager": "npm",
      "technology": {
        "name": "Express",
        "category": "framework",
        "vendor": "OpenJS Foundation"
      },
      "ownerTeam": "Backend Platform",
      "stewardTeams": [
        "Backend Platform"
      ],
      "policies": [],
      "approvals": [
        {
          "team": "Backend Platform",
          "time": "invest",
          "approvedAt": "2024-01-15",
          "notes": "Primary web framework",
          "approvedBy": "Tech Lead"
        }
      ]
    },
    {
      "componentName": "typescript",
      "packageManager": "npm",
      "technology": {
        "name": "TypeScript",
        "category": "language",
        "vendor": "Microsoft"
      },
      "ownerTeam": "Frontend Platform",
      "stewardTeams": [
        "Frontend Platform",
        "Platform Team"
      ],
      "policies": [],
      "approvals": [
        {
          "team": "Frontend Platform",
          "time": "invest",
          "approvedAt": "2024-01-15",
          "notes": "Required for all new projects",
          "approvedBy": "Tech Lead"
        },
        {
          "team": "Platform Team",
          "time": "invest",
          "approvedAt": "2024-01-15",
          "notes": "Primary language for all Platform Team projects",
          "approvedBy": "Platform Lead"
        }
      ]
    },
    {
      "componentName": "jquery",
      "packageManager": "npm",
      "technology": {
        "name": "jQuery",
        "category": "library",
        "vendor": "jQuery Foundation"
      },
      "ownerTeam": "Frontend Platform",
      "stewardTeams": [
        "Frontend Platform"
      ],
      "policies": [
        "Migration Target Required",
        "High Risk Technology Approval"
      ],
      "approvals": [
        {
          "team": "Frontend Platform",
          "time": "eliminate",
          "approvedAt": "2020-01-01",
          "deprecatedAt": "2023-01-01",
          "eolDate": "2025-12-31",
          "migrationTarget": "React",
          "notes": "Phase out - do not use in any projects",
          "approvedBy": "Tech Lead"
        }
      ]
    },
    {
      "componentName": "lodash",
      "packageManager": "npm",
      "technology": {
        "name": "Lodash",
        "category": "library",
        "vendor": "Lodash"
      },
      "ownerTeam": "Frontend Platform",
      "stewardTeams": [
        "Frontend Platform"
      ],
      "policies": [
        "Migration Target Required"
      ],
      "approvals": [
        {
          "team": "Frontend Platform",
          "time": "migrate",
          "approvedAt": "2022-01-01",
          "deprecatedAt": "2024-06-01",
          "migrationTarget": "Native ES6+",
          "notes": "Migrate to native JavaScript methods",
          "approvedBy": "Tech Lead"
        }
      ]
    }
  ]
}
